setup.py
src/rdvac6.py
src/rdvac6.egg-info/PKG-INFO
src/rdvac6.egg-info/SOURCES.txt
src/rdvac6.egg-info/dependency_links.txt
src/rdvac6.egg-info/top_level.txt