Metadata-Version: 2.1
Name: rdvac6
Version: 0.0.2
Summary:  A demo app for Text Classification using LSTM Model
Author: Lagisetty Ravikiran
Author-email: kiranlravi8@gmail.com
